{
  "T1001": "Kwando Kickboxing",
  "T1002": "Pull Ups",
  "T1004": "Push Ups",
  "T1005": "Skipping Rope",
  "T1006": "Sit Ups",
  "T1007": "Burpees",
  "T1009": "Jumping Jacks",
  "T1010": "Planks",
  "T1011": "Dumbbell Side Bends",
  "T1013": "High Knees",
  "T1014": "Box Jumps",
  "T1015": "Seated Front Press",
  "T1017": "Lateral Dumbbell Raise",
  "T1018": "Front Arm Raise",
  "T1019": "Upright Row",
  "T1020": "Bent Over Lateral Raise",
  "T1021": "Dumbbell Biceps Curls",
  "T1022": "Low Pulley Biceps Curls",
  "T1023": "Seated Dumbbell Concentration Curls",
  "T1024": "Preacher Curls",
  "T1025": "Triceps Pushdowns",
  "T1026": "Reverse Grip Tricep Pushdown",
  "T1027": "Barbell Lying Tricep Extensions",
  "T1028": "Tricep Kickbacks",
  "T1029": "Seated Dumbbell Triceps Extensions",
  "T1030": "Wrist Curls",
  "T1031": "Reverse Wrist Curls",
  "T1032": "Hanging Leg Raise",
  "T1033": "Bridge",
  "T1034": "Incline Leg Raise",
  "T1035": "Upright Leg Raise",
  "T1036": "Machine Crunches",
  "T1037": "High Pulley Crunches",
  "T1038": "Seated Leg Raise",
  "T1039": "Trunk Rotations",
  "T1040": "Oblique V Ups",
  "T1041": "Bench Press",
  "T1042": "Incline Bench Press",
  "T1043": "Decline Bench Press",
  "T1044": "Incline Dumbbell Flys",
  "T1045": "Dumbbell Flys",
  "T1046": "Low Cable Flys",
  "T1047": "Pec Deck Flys",
  "T1048": "Standing Cable Crossover",
  "T1049": "Dumbbell Pullover",
  "T1050": "Barbell Pullover",
  "T1051": "Parallel Bar Dips",
  "T1052": "Seated Lat Pulldowns",
  "T1053": "Seated Cable Row",
  "T1054": "Barbell Row",
  "T1055": "Dumbbell Row",
  "T1056": "Machine Hyperextention",
  "T1057": "Back Extensions",
  "T1058": "Dumbbell Shrugs",
  "T1059": "Barbell Shrugs",
  "T1060": "Step Up Jumps",
  "T1061": "Squats",
  "T1063": "Cable Glute Kickbacks",
  "T1064": "Dumbbell Lunges",
  "T1065": "Incline Leg Press",
  "T1066": "Leg Extensions",
  "T1067": "Deadlifts",
  "T1068": "T Bar Rows",
  "T1069": "Lying Leg Curls",
  "T1070": "Standing Calf Raises",
  "T1071": "Press The Neck Forward",
  "T1072": "Lying Face Down Plate Neck Resistance",
  "T1073": "Lying Face Up Plate Neck Resistance",
  "T1074": "Seated Head Harness Neck Resistance",
  "T1075": "Neck Bridge Prone",
  "T1076": "Bicycle Crunches",
  "T1077": "Face Down Jumping Jacks",
  "T1078": "Squat Jumps",
  "T1079": "Mountain Climbers",
  "T1080": "Battle Ropes",
  "T1081": "Trx Suspended Crunches",
  "T1082": "Trx Suspended Chest Flys",
  "T1083": "Trx Suspended Back Flys",
  "T1084": "Trx Suspended Leg Curl",
  "T1085": "Trx Suspended Biceps Curl",
  "T1086": "Trx Suspended Split Squat",
  "T1087": "Trx Suspended Abdominal Fallout",
  "T1088": "Exercise Ball Crunches",
  "T1089": "Exercise Ball Pull In",
  "T1090": "Exercise Ball Bridges",
  "T1091": "Exercise Ball Hyperextensions",
  "T1092": "Crunch Legs On Exercise Ball",
  "T1093": "Supine Overhead Ball Throw",
  "T1094": "Supine Chest Ball Throw",
  "T1095": "Backward Ball Throw",
  "T1096": "Standing Overhead Ball Throw",
  "T1097": "Overhead Ball Slam",
  "T1098": "Medicine Ball Push Ups",
  "T1099": "Bosu Ball Squats",
  "T1100": "Bosu Ball Push Ups",
  "T1101": "Bosu Ball Crunches",
  "T1103": "Lateral Band Walks",
  "T1104": "Chest Flys With Bands",
  "T1105": "Bench Press With Bands",
  "T1106": "Reverse Flys With Bands",
  "T1107": "Lateral Raises With Bands",
  "T1108": "Front Raises With Bands",
  "T1109": "Biceps Curls With Bands",
  "T1110": "Deadlifts With Bands",
  "T1112": "Thigh Abductor",
  "T1113": "Prone Hip Circles",
  "T1114": "Hip Adductions With Bands",
  "T1115": "Thigh Adductor",
  "T1116": "Standing Side Leg Raises",
  "T1117": "Power Squats",
  "T1120": "Warm Up",
  "T1121": "Training",
  "T1122": "Cool Down",
  "T1123": "Rest",
  "T1126": "Swing Your Arms Quickly In Place",
  "T1127": "Trot Quickly In Place",
  "T1128": "Hands On The Wall And High Knees",
  "T1129": "Fast Small Amplitude Wheel Run",
  "T1130": "Back Leg Kick Run",
  "T1131": "Run Fast Frequency At A Fast Pace",
  "T1132": "Lie On Your Back A Hip",
  "T1133": "Unilateral Supine Buttocks Lift Hip Lif",
  "T1134": "Push To Run After",
  "T1135": "The Wheels Run",
  "T1136": "Jumping Lunges",
  "T1137": "Lunge With Your Knees Up",
  "T1138": "Lunge Leg Lifts",
  "T1139": "Lunge And Jump Forward",
  "T1141": "Lie On One Leg Supine Hip And Knee",
  "T1142": "Lie On And High Knees",
  "T1143": "Side Bridge Wing Arm And Swing Leg",
  "T1144": "One Leg Deadlifts And Knee Lifting",
  "T1145": "Trunk Rotations",
  "T1146": "Lie On Your Back Alternately Touching Y",
  "T1147": "Sitting Scissors Kick",
  "T1148": "Plank Push Up",
  "T1149": "Crunch",
  "T1150": "Bird Dog Type",
  "T1151": "Kneeling Position And Do The Top Hip",
  "T1152": "Lunge Down",
  "T1153": "Lunge Sideways From Hip To Hip",
  "T1154": "Lunge Up With A Heavy Bow",
  "T1155": "Standing Leg Lifts",
  "T1156": "Windshield Wiper",
  "T1157": "Power Point",
  "T1158": "Super Push Up",
  "T1159": "Leg Raise Toe To Bar",
  "T1160": "Single Leg Bridge",
  "T1161": "The L Sit",
  "T1162": "Side Plank Rotation",
  "T1163": "Turkish Get Up",
  "T1164": "Split Bench Squat",
  "T1165": "Dips",
  "T1166": "Box Step Ups",
  "T1167": "Single Leg Squats",
  "T1168": "Handstands",
  "T1169": "Incline Walking",
  "T1170": "Incline Walking",
  "T1171": "Hanging Windshield Wiper",
  "T1173": "Lower Oblique Load Roll",
  "T1174": "Ski Step",
  "T1175": "Back And Forth Step",
  "T1176": "Snatches",
  "T1177": "One Arm Kettlebell Swings",
  "T1178": "Two Arm Kettlebell Swings",
  "T1179": "One Arm Kettlebell Military Press To The Side",
  "T1180": "Kettlebell Windmill",
  "T1181": "J Lo S",
  "T1182": "Crawl On The Ground",
  "T1183": "Lean Over And Touch Your Shoulders Alte",
  "T1184": "Kneeling Push Ups",
  "T1185": "Side Plank",
  "T1186": "Archer",
  "T1187": "Single Leg Deadlift",
  "T1188": "Curtsey Squat",
  "T1189": "Stretch Strap Squat",
  "T1190": "Lunge With Elastic Band",
  "T1191": "Stretch Tape Squats Sideways",
  "T1192": "Elastic Band Plate Pull Down",
  "T1193": "Stretch Strap Bicycle On Your Back",
  "T1194": "Elastic Band Bends Hip And Pulls Back",
  "T1195": "Stretch Tape Squat Pull Back",
  "T1196": "Stretch With Lunge To Lift Knees",
  "T1197": "Elastic Belt Swallow Balance",
  "T1198": "The Elastic Band Bends The Hip And Pres",
  "T1199": "Spring With Lunge Quick Punch",
  "T1200": "Bounce A Boat",
  "T1201": "Bounce A Boat With A Lunge",
  "T1202": "Open Hand Grip",
  "T1203": "Half Crimp",
  "T1204": "Slope Hang",
  "T1205": "Hang With 90 Degree Elbow",
  "T1206": "Hang With 135 Degree Elbow",
  "T1207": "Indoor Rower",
  "T1211": "V Sit Hold",
  "T1212": "A Skips",
  "T1213": "B Skips",
  "T1214": "C Skips",
  "T1215": "Back Stretch",
  "T1216": "Side Plank With Leg Raise",
  "T1217": "Lateral Squats Or Side Squats",
  "T1218": "Single Leg High Knee Jump",
  "T1219": "Single Leg Hip Bridge",
  "T1220": "Handstand Push Up",
  "T1221": "Inverse Nordic Curl",
  "T1222": "Leg Swing Front And Back",
  "T1223": "Prone Cobra",
  "T1224": "Lunge Pulls",
  "T1225": "Walking Lunges",
  "T1226": "Reverse Lunge",
  "T1227": "Clapping Push Up",
  "T1228": "Shoulder Stretch",
  "T1229": "Glute Bridge Hold",
  "T1230": "Saw Plank",
  "T1231": "Wall Sit",
  "T1232": "Wide Grip Push Up",
  "T1233": "Donkey Kicks",
  "T1234": "Cat Cow Stretch",
  "T1235": "Pike Push Up",
  "T1236": "Straight Leg Run Or Bounding",
  "T1237": "Offset Push Up",
  "T1238": "Plank With Lateral Movement",
  "T1239": "Plank With Rotation",
  "T1240": "Frog Pose",
  "T1241": "Incline Push Up",
  "T1242": "Fingertip Push Up",
  "T1243": "Dead Bug",
  "T1244": "Glute Stretch",
  "T1245": "Decline Push Up",
  "T1246": "Calf Stretch",
  "T1247": "Chest Stretch",
  "T1248": "Thoracic Spine Rotation",
  "T1249": "Bird Dog Balance",
  "T1250": "Supine Oblique Wood Chop",
  "T1251": "Supine Cobra",
  "T1252": "Supine Knee Tucks",
  "T1253": "Close Grip Push Up",
  "T1254": "Standing Forward Bend",
  "T1255": "Standing Hamstring Curl",
  "T1256": "Quadriceps Stretch",
  "T1257": "Standing Knee To Elbow",
  "T1258": "Lucky Cat",
  "T1259": "Plank Jacks 2",
  "T1260": "Straight Leg Hops",
  "T1261": "Diamond Push Up",
  "T1262": "Greatest Stretch",
  "T1263": "Lateral Leg Swings",
  "T1264": "Bicep Stretch",
  "T1265": "Tricep Stretch",
  "T1266": "Hamstring Stretch",
  "T1267": "Inner Thigh Stretch",
  "T1268": "Outer Thigh Stretch",
  "T1269": "Knee Hug",
  "T1270": "Dynamic Stretch Crossbody Calf Hug",
  "T1271": "Dynamic Stretch Quad Stretch With Reach",
  "T1272": "Dynamic Stretch Toe Touch Sweep",
  "T1273": "Single Leg Hops",
  "T1274": "Lunge Stretch",
  "T1275": "Single Leg Calf Raise",
  "T1276": "Prone As",
  "T1277": "Prone Is",
  "T1278": "Prone Ys",
  "T1279": "Prone Ts",
  "T1280": "Prone Ws",
  "T1281": "Ez Bar Curl",
  "T1282": "Front Squat",
  "T1283": "Barbell Front Raise",
  "T1284": "Barbell Good Morning",
  "T1285": "Power Clean",
  "T1286": "Behind The Neck Press",
  "T1287": "Romanian Deadlift",
  "T1288": "Military Press",
  "T1289": "Hip Thrust",
  "T1290": "Sumo Deadlift",
  "T1291": "Box Squat",
  "T1292": "Zercher Squat",
  "T1293": "Close Grip Bench Press",
  "T1294": "Barbell Stiff Leg Deadlift",
  "T1295": "Sumo Squat",
  "T1296": "Step Ups",
  "T1297": "Arnold Press",
  "T1298": "Reverse Curl",
  "T1299": "Plank Row",
  "T1300": "Weighted Jump Squats",
  "T1301": "Goblet Squat",
  "T1302": "Dumbbell Bench Press",
  "T1303": "Incline Dumbbell Bench Press",
  "T1304": "Decline Dumbbell Bench Press",
  "T1305": "Dumbbell Romanian Deadlift",
  "T1306": "Close Grip Dumbbell Bench Press",
  "T1307": "Dumbbell Snatch",
  "T1308": "Hammer Curl",
  "T1309": "One Arm Dumbbell Row",
  "T1310": "Farmers Walk",
  "T1311": "Weighted Hanging Leg Raise",
  "T1312": "Dumbbell Good Morning",
  "T1313": "Seated Calf Raise",
  "T1314": "Dumbbell Thruster",
  "T1315": "Single Leg Shoulder Press",
  "T1316": "Floor Press",
  "T1317": "Clamshell",
  "T1318": "Seated Resistance Band Tibialis Raise",
  "T1319": "Banded Kneeling Hip Extensions",
  "T1320": "Banded Shoulder External Rotation",
  "T1321": "Banded Hip Abduction",
  "T1322": "Banded Hip Flexion",
  "T1323": "Banded Hip Extension",
  "T1324": "Banded Press",
  "T1325": "Lying Leg Curls With Resistance Band",
  "T1326": "Banded Ankle Inversion",
  "T1327": "Banded Ankle Eversion",
  "T1328": "Barbell Plate Halo",
  "T1329": "Single Arm Scap Pulls",
  "T1330": "Archer Pull Up",
  "T1331": "Reverse Hack Squat",
  "T1332": "Hack Squat Good Morning",
  "T1333": "Scapular Pull Up",
  "T1334": "Lateral Raise Machine",
  "T1335": "Bicep Curl Machine",
  "T1336": "Machine Reverse Fly",
  "T1337": "Shoulder Press Machine",
  "T1338": "Chest Press Machine",
  "T1339": "Smith Machine Squat",
  "T1340": "Supine Pull Ups",
  "T1341": "Triceps Pushdown Machine",
  "T1342": "Lat Pulldowns",
  "T1343": "Bosu Ball High Knee Lunge",
  "T1344": "Bosu Ball Single Leg Deadlift",
  "T1345": "Bosu Ball Single Leg Hold",
  "T1346": "Single Leg Curl",
  "T1347": "Exercise Ball Circles",
  "T1348": "Exercise Ball Buzzsaw Plank",
  "T1349": "Exercise Ball Plank",
  "T1350": "Single Arm Lat Pulldown",
  "T1351": "Behind The Neck Pulldowns",
  "T1352": "Face Pull",
  "T1353": "Cable Lateral Raise",
  "T1354": "Cable Rotation",
  "T1355": "Kneeling Cable Woodchop",
  "T1356": "Cable Reverse Fly",
  "T1357": "Cable Pull Through",
  "T1358": "Straight Arm Pulldown",
  "T1359": "Kneeling Anti Rotational Press",
  "T1360": "Hangboard Pull Ups",
  "T1361": "Rainbow Slam",
  "T1362": "Med Ball Push Press",
  "T1363": "Twist Throw",
  "T1364": "Russian Twist Med Ball Slam",
  "T1365": "Nordic Hamstring Curl",
  "T1366": "Box Step Up Knee Drive",
  "T1367": "Reverse Step Down",
  "T1368": "Copenhagen Plank",
  "T1369": "Kneeling Ab Wheel Rollout",
  "T1370": "Wrist Roller",
  "T1371": "Hex Bar Deadlift",
  "T1372": "Battle Rope Double Waves",
  "T1373": "Battle Rope In And Out Waves",
  "T1374": "Battle Rope Slams",
  "T1375": "Battle Rope Alternating Waves",
  "T1376": "Foot Rolling",
  "T1377": "One Arm Bar Hangs",
  "T1378": "Stick Warmup 1",
  "T1379": "Stick Warmup 2",
  "T1380": "Stick Warmup 3",
  "T1381": "Smith Machine Reverse Kickbacks",
  "T1382": "Smith Machine Shoulder Press",
  "T1383": "Foam Rolling Tibialis Anteriors",
  "T1384": "Foam Rolling Hips",
  "T1385": "Foam Rolling Hamstrings",
  "T1386": "Foam Rolling It Bands",
  "T1387": "Foam Rolling Quads",
  "T1388": "Foam Rolling Adductors",
  "T1389": "Foam Rolling Calves",
  "T1390": "Foam Rolling Chest",
  "T1391": "Foam Rolling Upper Back",
  "T1392": "Single Arm Overhead Farmers Walk",
  "T1393": "Skierg",
  "T1394": "Sledpush",
  "T1395": "Sledpull",
  "T1396": "Burpee",
  "T1397": "Wallballs"
}
